{
  "$type": "Bespoke.Sph.Domain.WorkflowDefinition, domain.sph",
  "ActivityCollection": {
    "$type": "Bespoke.Sph.Domain.ObjectCollection`1[[Bespoke.Sph.Domain.Activity, domain.sph]], domain.sph",
    "$values": [
      {
        "$type": "Bespoke.Sph.Domain.NotificationActivity, domain.sph",
        "From": "admin@@sph.my",
        "Subject": "Child Email @Model.EmailSubject",
        "Body": "Child Email",
        "To": "child-email@gmail.com",
        "UserName": null,
        "Cc": null,
        "Bcc": null,
        "IsHtmlEmail": false,
        "IsMessageSuppressed": false,
        "Retry": null,
        "RetryInterval": null,
        "IsAsync": false,
        "ExecutedCode": null,
        "ExecutingCode": null,
        "TypeName": "Notification",
        "OtherMethodCollection": {
          "$type": "Bespoke.Sph.Domain.ObjectCollection`1[[Bespoke.Sph.Domain.Codes.Method, domain.sph]], domain.sph",
          "$values": [
            {
              "$type": "Bespoke.Sph.Domain.Codes.Method, domain.sph",
              "Comment": null,
              "AccessModifier": "Internal",
              "ReturnType": null,
              "Name": null,
              "FileName": null,
              "Code": "   private async Task<string> TransformFromChildEmailAsync(string template)\r\n   {\r\n\r\n            var razor = ObjectBuilder.GetObject<ITemplateEngine>();\r\n            return await razor.GenerateAsync(template, this).ConfigureAwait(false);   }\r\n",
              "Body": "",
              "IsVirtual": false,
              "IsOverride": false,
              "IsStatic": false,
              "ArgumentCollection": {
                "$type": "Bespoke.Sph.Domain.ObjectCollection`1[[Bespoke.Sph.Domain.MethodArg, domain.sph]], domain.sph",
                "$values": []
              },
              "AttributeCollection": {
                "$type": "Bespoke.Sph.Domain.ObjectCollection`1[[System.String, mscorlib]], domain.sph",
                "$values": []
              },
              "IsPartial": false,
              "ReturnTypeName": null
            },
            {
              "$type": "Bespoke.Sph.Domain.Codes.Method, domain.sph",
              "Comment": null,
              "AccessModifier": "Internal",
              "ReturnType": null,
              "Name": null,
              "FileName": null,
              "Code": "   private async Task<string> TransformToChildEmailAsync(string template)\r\n   {\r\n\r\n            var razor = ObjectBuilder.GetObject<ITemplateEngine>();\r\n            return await razor.GenerateAsync(template, this).ConfigureAwait(false);   }\r\n",
              "Body": "",
              "IsVirtual": false,
              "IsOverride": false,
              "IsStatic": false,
              "ArgumentCollection": {
                "$type": "Bespoke.Sph.Domain.ObjectCollection`1[[Bespoke.Sph.Domain.MethodArg, domain.sph]], domain.sph",
                "$values": []
              },
              "AttributeCollection": {
                "$type": "Bespoke.Sph.Domain.ObjectCollection`1[[System.String, mscorlib]], domain.sph",
                "$values": []
              },
              "IsPartial": false,
              "ReturnTypeName": null
            },
            {
              "$type": "Bespoke.Sph.Domain.Codes.Method, domain.sph",
              "Comment": null,
              "AccessModifier": "Internal",
              "ReturnType": null,
              "Name": null,
              "FileName": null,
              "Code": "   private async Task<string> TransformSubjectChildEmailAsync(string template)\r\n   {\r\n\r\n            var razor = ObjectBuilder.GetObject<ITemplateEngine>();\r\n            return await razor.GenerateAsync(template, this).ConfigureAwait(false);   }\r\n",
              "Body": "",
              "IsVirtual": false,
              "IsOverride": false,
              "IsStatic": false,
              "ArgumentCollection": {
                "$type": "Bespoke.Sph.Domain.ObjectCollection`1[[Bespoke.Sph.Domain.MethodArg, domain.sph]], domain.sph",
                "$values": []
              },
              "AttributeCollection": {
                "$type": "Bespoke.Sph.Domain.ObjectCollection`1[[System.String, mscorlib]], domain.sph",
                "$values": []
              },
              "IsPartial": false,
              "ReturnTypeName": null
            },
            {
              "$type": "Bespoke.Sph.Domain.Codes.Method, domain.sph",
              "Comment": null,
              "AccessModifier": "Internal",
              "ReturnType": null,
              "Name": null,
              "FileName": null,
              "Code": "   private async Task<string> TransformBodyChildEmailAsync(string template)\r\n   {\r\n\r\n            var razor = ObjectBuilder.GetObject<ITemplateEngine>();\r\n            return await razor.GenerateAsync(template, this).ConfigureAwait(false);   }\r\n",
              "Body": "",
              "IsVirtual": false,
              "IsOverride": false,
              "IsStatic": false,
              "ArgumentCollection": {
                "$type": "Bespoke.Sph.Domain.ObjectCollection`1[[Bespoke.Sph.Domain.MethodArg, domain.sph]], domain.sph",
                "$values": []
              },
              "AttributeCollection": {
                "$type": "Bespoke.Sph.Domain.ObjectCollection`1[[System.String, mscorlib]], domain.sph",
                "$values": []
              },
              "IsPartial": false,
              "ReturnTypeName": null
            }
          ]
        },
        "WorkflowDesigner": {
          "$type": "Bespoke.Sph.Domain.WorkflowDesigner, domain.sph",
          "X": 664,
          "Y": 80,
          "WebId": null
        },
        "IsInitiator": true,
        "NextActivityWebId": "1a3231ae-73b2-44b5-a3ac-0b933e392364",
        "Name": "Child Email",
        "TryScope": null,
        "CatchScope": null,
        "WebId": "5d690f35-b64d-4303-ddaa-d846644113bd"
      },
      {
        "$type": "Bespoke.Sph.Domain.EndActivity, domain.sph",
        "IsTerminating": false,
        "IsAsync": false,
        "ExecutedCode": null,
        "ExecutingCode": null,
        "TypeName": "End",
        "OtherMethodCollection": {
          "$type": "Bespoke.Sph.Domain.ObjectCollection`1[[Bespoke.Sph.Domain.Codes.Method, domain.sph]], domain.sph",
          "$values": []
        },
        "WorkflowDesigner": {
          "$type": "Bespoke.Sph.Domain.WorkflowDesigner, domain.sph",
          "X": 663,
          "Y": 402,
          "WebId": null
        },
        "IsInitiator": false,
        "NextActivityWebId": null,
        "Name": "End_1",
        "TryScope": null,
        "CatchScope": null,
        "WebId": "16d0effe-8e2d-4e25-c6b9-6b84241dbdb9"
      },
      {
        "$type": "Bespoke.Sph.Domain.ExpressionActivity, domain.sph",
        "Expression": "this.SimpleValue = this.EmailSubject + \" !!!!\";",
        "IsAsync": false,
        "ExecutedCode": null,
        "ExecutingCode": null,
        "TypeName": "Expression",
        "OtherMethodCollection": {
          "$type": "Bespoke.Sph.Domain.ObjectCollection`1[[Bespoke.Sph.Domain.Codes.Method, domain.sph]], domain.sph",
          "$values": []
        },
        "WorkflowDesigner": {
          "$type": "Bespoke.Sph.Domain.WorkflowDesigner, domain.sph",
          "X": 996,
          "Y": 289,
          "WebId": null
        },
        "IsInitiator": false,
        "NextActivityWebId": "16d0effe-8e2d-4e25-c6b9-6b84241dbdb9",
        "Name": "Init Simple Value",
        "TryScope": null,
        "CatchScope": null,
        "WebId": "1a3231ae-73b2-44b5-a3ac-0b933e392364"
      }
    ]
  },
  "VariableDefinitionCollection": {
    "$type": "Bespoke.Sph.Domain.ObjectCollection`1[[Bespoke.Sph.Domain.Variable, domain.sph]], domain.sph",
    "$values": [
      {
        "$type": "Bespoke.Sph.Domain.SimpleVariable, domain.sph",
        "Name": "EmailSubject",
        "TypeName": "System.String, mscorlib",
        "DefaultValue": "",
        "WebId": "bde25f5f-d4b5-4239-8111-3fed2e91b120"
      },
      {
        "$type": "Bespoke.Sph.Domain.SimpleVariable, domain.sph",
        "Name": "SimpleValue",
        "TypeName": "System.String, mscorlib",
        "DefaultValue": "",
        "WebId": "d05fc95f-dbff-407e-cc34-d5e11f481cbd"
      }
    ]
  },
  "ReferencedAssemblyCollection": {
    "$type": "Bespoke.Sph.Domain.ObjectCollection`1[[Bespoke.Sph.Domain.ReferencedAssembly, domain.sph]], domain.sph",
    "$values": []
  },
  "CorrelationSetCollection": {
    "$type": "Bespoke.Sph.Domain.ObjectCollection`1[[Bespoke.Sph.Domain.CorrelationSet, domain.sph]], domain.sph",
    "$values": []
  },
  "CorrelationTypeCollection": {
    "$type": "Bespoke.Sph.Domain.ObjectCollection`1[[Bespoke.Sph.Domain.CorrelationType, domain.sph]], domain.sph",
    "$values": []
  },
  "TryScopeCollection": {
    "$type": "Bespoke.Sph.Domain.ObjectCollection`1[[Bespoke.Sph.Domain.TryScope, domain.sph]], domain.sph",
    "$values": []
  },
  "Name": "Simple child workflow",
  "Note": "",
  "IsActive": true,
  "SchemaStoreId": "3228e384-d33d-44e1-b11d-f06ccc6c8a06",
  "Version": 1,
  "CreatedBy": "admin",
  "Id": "simple-child-workflow",
  "CreatedDate": "2016-03-12T16:23:17.8834533+08:00",
  "ChangedBy": "admin",
  "ChangedDate": "2016-03-12T17:01:11.6862339+08:00",
  "WebId": "d6ddf7c0-f3cd-4cbc-86b2-285aeaa8a289"
}