{
  "$type": "Bespoke.Sph.Domain.EntityDefinition, domain.sph",
  "CodeNamespace": "Bespoke.Dev_2002.Domain",
  "MemberCollection": {
    "$type": "Bespoke.Sph.Domain.ObjectCollection`1[[Bespoke.Sph.Domain.Member, domain.sph]], domain.sph",
    "$values": [
      {
        "$type": "Bespoke.Sph.Domain.Member, domain.sph",
        "FullName": null,
        "MemberCollection": {
          "$type": "Bespoke.Sph.Domain.ObjectCollection`1[[Bespoke.Sph.Domain.Member, domain.sph]], domain.sph",
          "$values": []
        },
        "FieldPermissionCollection": {
          "$type": "Bespoke.Sph.Domain.ObjectCollection`1[[Bespoke.Sph.Domain.FieldPermission, domain.sph]], domain.sph",
          "$values": []
        },
        "Name": "Mrn",
        "TypeName": "System.String, mscorlib",
        "IsNullable": false,
        "IsNotIndexed": false,
        "IsAnalyzed": false,
        "IsFilterable": true,
        "IsExcludeInAll": false,
        "Boost": 6,
        "WebId": "8bcd9193-40eb-4555-8110-6f04c7d6209a"
      },
      {
        "$type": "Bespoke.Sph.Domain.Member, domain.sph",
        "FullName": null,
        "MemberCollection": {
          "$type": "Bespoke.Sph.Domain.ObjectCollection`1[[Bespoke.Sph.Domain.Member, domain.sph]], domain.sph",
          "$values": []
        },
        "FieldPermissionCollection": {
          "$type": "Bespoke.Sph.Domain.ObjectCollection`1[[Bespoke.Sph.Domain.FieldPermission, domain.sph]], domain.sph",
          "$values": []
        },
        "Name": "FullName",
        "TypeName": "System.String, mscorlib",
        "IsNullable": false,
        "IsNotIndexed": false,
        "IsAnalyzed": true,
        "IsFilterable": true,
        "IsExcludeInAll": false,
        "Boost": 5,
        "WebId": "16d2daae-ea30-4ea4-b125-a426014d8422"
      },
      {
        "$type": "Bespoke.Sph.Domain.Member, domain.sph",
        "FullName": null,
        "MemberCollection": {
          "$type": "Bespoke.Sph.Domain.ObjectCollection`1[[Bespoke.Sph.Domain.Member, domain.sph]], domain.sph",
          "$values": []
        },
        "FieldPermissionCollection": {
          "$type": "Bespoke.Sph.Domain.ObjectCollection`1[[Bespoke.Sph.Domain.FieldPermission, domain.sph]], domain.sph",
          "$values": []
        },
        "Name": "Dob",
        "TypeName": "System.DateTime, mscorlib",
        "IsNullable": false,
        "IsNotIndexed": false,
        "IsAnalyzed": false,
        "IsFilterable": false,
        "IsExcludeInAll": false,
        "Boost": 0,
        "WebId": "846da964-0c28-440a-926d-e08293392892"
      },
      {
        "$type": "Bespoke.Sph.Domain.Member, domain.sph",
        "FullName": null,
        "MemberCollection": {
          "$type": "Bespoke.Sph.Domain.ObjectCollection`1[[Bespoke.Sph.Domain.Member, domain.sph]], domain.sph",
          "$values": []
        },
        "FieldPermissionCollection": {
          "$type": "Bespoke.Sph.Domain.ObjectCollection`1[[Bespoke.Sph.Domain.FieldPermission, domain.sph]], domain.sph",
          "$values": []
        },
        "Name": "Gender",
        "TypeName": "System.String, mscorlib",
        "IsNullable": false,
        "IsNotIndexed": false,
        "IsAnalyzed": false,
        "IsFilterable": true,
        "IsExcludeInAll": false,
        "Boost": 0,
        "WebId": "735865c9-2a2a-47fa-96cc-9ca12eab432d"
      },
      {
        "$type": "Bespoke.Sph.Domain.Member, domain.sph",
        "FullName": null,
        "MemberCollection": {
          "$type": "Bespoke.Sph.Domain.ObjectCollection`1[[Bespoke.Sph.Domain.Member, domain.sph]], domain.sph",
          "$values": []
        },
        "FieldPermissionCollection": {
          "$type": "Bespoke.Sph.Domain.ObjectCollection`1[[Bespoke.Sph.Domain.FieldPermission, domain.sph]], domain.sph",
          "$values": []
        },
        "Name": "Religion",
        "TypeName": "System.String, mscorlib",
        "IsNullable": false,
        "IsNotIndexed": false,
        "IsAnalyzed": false,
        "IsFilterable": true,
        "IsExcludeInAll": false,
        "Boost": 0,
        "WebId": "25e424ca-090e-4572-860d-225fc188448e"
      },
      {
        "$type": "Bespoke.Sph.Domain.Member, domain.sph",
        "FullName": null,
        "MemberCollection": {
          "$type": "Bespoke.Sph.Domain.ObjectCollection`1[[Bespoke.Sph.Domain.Member, domain.sph]], domain.sph",
          "$values": []
        },
        "FieldPermissionCollection": {
          "$type": "Bespoke.Sph.Domain.ObjectCollection`1[[Bespoke.Sph.Domain.FieldPermission, domain.sph]], domain.sph",
          "$values": []
        },
        "Name": "Race",
        "TypeName": "System.String, mscorlib",
        "IsNullable": false,
        "IsNotIndexed": false,
        "IsAnalyzed": false,
        "IsFilterable": true,
        "IsExcludeInAll": false,
        "Boost": 0,
        "WebId": "7f16952d-f2d3-4553-8f89-d6b8447c510f"
      },
      {
        "$type": "Bespoke.Sph.Domain.Member, domain.sph",
        "FullName": null,
        "MemberCollection": {
          "$type": "Bespoke.Sph.Domain.ObjectCollection`1[[Bespoke.Sph.Domain.Member, domain.sph]], domain.sph",
          "$values": []
        },
        "FieldPermissionCollection": {
          "$type": "Bespoke.Sph.Domain.ObjectCollection`1[[Bespoke.Sph.Domain.FieldPermission, domain.sph]], domain.sph",
          "$values": []
        },
        "Name": "RegisteredDate",
        "TypeName": "System.DateTime, mscorlib",
        "IsNullable": false,
        "IsNotIndexed": false,
        "IsAnalyzed": false,
        "IsFilterable": false,
        "IsExcludeInAll": false,
        "Boost": 0,
        "WebId": "a23f7302-b927-45da-8724-c992d20302ea"
      },
      {
        "$type": "Bespoke.Sph.Domain.Member, domain.sph",
        "FullName": null,
        "MemberCollection": {
          "$type": "Bespoke.Sph.Domain.ObjectCollection`1[[Bespoke.Sph.Domain.Member, domain.sph]], domain.sph",
          "$values": []
        },
        "FieldPermissionCollection": {
          "$type": "Bespoke.Sph.Domain.ObjectCollection`1[[Bespoke.Sph.Domain.FieldPermission, domain.sph]], domain.sph",
          "$values": []
        },
        "Name": "IdentificationNo",
        "TypeName": "System.String, mscorlib",
        "IsNullable": false,
        "IsNotIndexed": false,
        "IsAnalyzed": false,
        "IsFilterable": false,
        "IsExcludeInAll": false,
        "Boost": 5,
        "WebId": "8a54ac46-286e-4e75-bf1a-274666dcffa0"
      },
      {
        "$type": "Bespoke.Sph.Domain.Member, domain.sph",
        "FullName": null,
        "MemberCollection": {
          "$type": "Bespoke.Sph.Domain.ObjectCollection`1[[Bespoke.Sph.Domain.Member, domain.sph]], domain.sph",
          "$values": []
        },
        "FieldPermissionCollection": {
          "$type": "Bespoke.Sph.Domain.ObjectCollection`1[[Bespoke.Sph.Domain.FieldPermission, domain.sph]], domain.sph",
          "$values": []
        },
        "Name": "PassportNo",
        "TypeName": "System.String, mscorlib",
        "IsNullable": false,
        "IsNotIndexed": false,
        "IsAnalyzed": false,
        "IsFilterable": false,
        "IsExcludeInAll": false,
        "Boost": 5,
        "WebId": "40cad2f8-1345-49a9-b210-01e8ec3c641f"
      },
      {
        "$type": "Bespoke.Sph.Domain.Member, domain.sph",
        "FullName": null,
        "MemberCollection": {
          "$type": "Bespoke.Sph.Domain.ObjectCollection`1[[Bespoke.Sph.Domain.Member, domain.sph]], domain.sph",
          "$values": []
        },
        "FieldPermissionCollection": {
          "$type": "Bespoke.Sph.Domain.ObjectCollection`1[[Bespoke.Sph.Domain.FieldPermission, domain.sph]], domain.sph",
          "$values": []
        },
        "Name": "Nationality",
        "TypeName": "System.String, mscorlib",
        "IsNullable": false,
        "IsNotIndexed": false,
        "IsAnalyzed": false,
        "IsFilterable": false,
        "IsExcludeInAll": false,
        "Boost": 0,
        "WebId": "d0581eed-a29e-4723-ba15-85ae6cfe6712"
      },
      {
        "$type": "Bespoke.Sph.Domain.Member, domain.sph",
        "FullName": null,
        "MemberCollection": {
          "$type": "Bespoke.Sph.Domain.ObjectCollection`1[[Bespoke.Sph.Domain.Member, domain.sph]], domain.sph",
          "$values": [
            {
              "$type": "Bespoke.Sph.Domain.Member, domain.sph",
              "FullName": null,
              "MemberCollection": {
                "$type": "Bespoke.Sph.Domain.ObjectCollection`1[[Bespoke.Sph.Domain.Member, domain.sph]], domain.sph",
                "$values": []
              },
              "FieldPermissionCollection": {
                "$type": "Bespoke.Sph.Domain.ObjectCollection`1[[Bespoke.Sph.Domain.FieldPermission, domain.sph]], domain.sph",
                "$values": []
              },
              "Name": "FullName",
              "TypeName": "System.String, mscorlib",
              "IsNullable": false,
              "IsNotIndexed": false,
              "IsAnalyzed": true,
              "IsFilterable": false,
              "IsExcludeInAll": false,
              "Boost": 0,
              "WebId": "d5f801b0-d07d-4bd3-b0a9-451ea8c50a2f"
            },
            {
              "$type": "Bespoke.Sph.Domain.Member, domain.sph",
              "FullName": null,
              "MemberCollection": {
                "$type": "Bespoke.Sph.Domain.ObjectCollection`1[[Bespoke.Sph.Domain.Member, domain.sph]], domain.sph",
                "$values": []
              },
              "FieldPermissionCollection": {
                "$type": "Bespoke.Sph.Domain.ObjectCollection`1[[Bespoke.Sph.Domain.FieldPermission, domain.sph]], domain.sph",
                "$values": []
              },
              "Name": "Relationship",
              "TypeName": "System.String, mscorlib",
              "IsNullable": false,
              "IsNotIndexed": false,
              "IsAnalyzed": false,
              "IsFilterable": false,
              "IsExcludeInAll": false,
              "Boost": 0,
              "WebId": "db2f4611-86d3-4aad-9458-c5d30d770f47"
            },
            {
              "$type": "Bespoke.Sph.Domain.Member, domain.sph",
              "FullName": null,
              "MemberCollection": {
                "$type": "Bespoke.Sph.Domain.ObjectCollection`1[[Bespoke.Sph.Domain.Member, domain.sph]], domain.sph",
                "$values": []
              },
              "FieldPermissionCollection": {
                "$type": "Bespoke.Sph.Domain.ObjectCollection`1[[Bespoke.Sph.Domain.FieldPermission, domain.sph]], domain.sph",
                "$values": []
              },
              "Name": "MobilePhone",
              "TypeName": "System.String, mscorlib",
              "IsNullable": false,
              "IsNotIndexed": false,
              "IsAnalyzed": false,
              "IsFilterable": false,
              "IsExcludeInAll": false,
              "Boost": 0,
              "WebId": "6a4f773a-261b-41bf-b9e2-329ed5ec064b"
            },
            {
              "$type": "Bespoke.Sph.Domain.Member, domain.sph",
              "FullName": null,
              "MemberCollection": {
                "$type": "Bespoke.Sph.Domain.ObjectCollection`1[[Bespoke.Sph.Domain.Member, domain.sph]], domain.sph",
                "$values": []
              },
              "FieldPermissionCollection": {
                "$type": "Bespoke.Sph.Domain.ObjectCollection`1[[Bespoke.Sph.Domain.FieldPermission, domain.sph]], domain.sph",
                "$values": []
              },
              "Name": "Email",
              "TypeName": "System.String, mscorlib",
              "IsNullable": false,
              "IsNotIndexed": false,
              "IsAnalyzed": true,
              "IsFilterable": false,
              "IsExcludeInAll": false,
              "Boost": 0,
              "WebId": "e815f1c0-cc63-44df-a5ce-fa1a0879da97"
            },
            {
              "$type": "Bespoke.Sph.Domain.Member, domain.sph",
              "FullName": null,
              "MemberCollection": {
                "$type": "Bespoke.Sph.Domain.ObjectCollection`1[[Bespoke.Sph.Domain.Member, domain.sph]], domain.sph",
                "$values": []
              },
              "FieldPermissionCollection": {
                "$type": "Bespoke.Sph.Domain.ObjectCollection`1[[Bespoke.Sph.Domain.FieldPermission, domain.sph]], domain.sph",
                "$values": []
              },
              "Name": "Telephone",
              "TypeName": "System.String, mscorlib",
              "IsNullable": false,
              "IsNotIndexed": false,
              "IsAnalyzed": false,
              "IsFilterable": false,
              "IsExcludeInAll": false,
              "Boost": 0,
              "WebId": "583f40e6-986b-453c-a84c-88e3f4eeb37d"
            }
          ]
        },
        "FieldPermissionCollection": {
          "$type": "Bespoke.Sph.Domain.ObjectCollection`1[[Bespoke.Sph.Domain.FieldPermission, domain.sph]], domain.sph",
          "$values": []
        },
        "Name": "NextOfKin",
        "TypeName": "System.Object, mscorlib",
        "IsNullable": false,
        "IsNotIndexed": false,
        "IsAnalyzed": false,
        "IsFilterable": false,
        "IsExcludeInAll": false,
        "Boost": 0,
        "WebId": "c1b8c2a6-a5bc-4ce0-bb0f-020261f4d460"
      },
      {
        "$type": "Bespoke.Sph.Domain.Member, domain.sph",
        "FullName": null,
        "MemberCollection": {
          "$type": "Bespoke.Sph.Domain.ObjectCollection`1[[Bespoke.Sph.Domain.Member, domain.sph]], domain.sph",
          "$values": [
            {
              "$type": "Bespoke.Sph.Domain.Member, domain.sph",
              "FullName": null,
              "MemberCollection": {
                "$type": "Bespoke.Sph.Domain.ObjectCollection`1[[Bespoke.Sph.Domain.Member, domain.sph]], domain.sph",
                "$values": []
              },
              "FieldPermissionCollection": {
                "$type": "Bespoke.Sph.Domain.ObjectCollection`1[[Bespoke.Sph.Domain.FieldPermission, domain.sph]], domain.sph",
                "$values": []
              },
              "Name": "Street",
              "TypeName": "System.String, mscorlib",
              "IsNullable": false,
              "IsNotIndexed": false,
              "IsAnalyzed": false,
              "IsFilterable": false,
              "IsExcludeInAll": false,
              "Boost": 0,
              "WebId": "76267898-ff46-437f-920b-27ce07462229"
            },
            {
              "$type": "Bespoke.Sph.Domain.Member, domain.sph",
              "FullName": null,
              "MemberCollection": {
                "$type": "Bespoke.Sph.Domain.ObjectCollection`1[[Bespoke.Sph.Domain.Member, domain.sph]], domain.sph",
                "$values": []
              },
              "FieldPermissionCollection": {
                "$type": "Bespoke.Sph.Domain.ObjectCollection`1[[Bespoke.Sph.Domain.FieldPermission, domain.sph]], domain.sph",
                "$values": []
              },
              "Name": "Street2",
              "TypeName": "System.String, mscorlib",
              "IsNullable": false,
              "IsNotIndexed": false,
              "IsAnalyzed": false,
              "IsFilterable": false,
              "IsExcludeInAll": false,
              "Boost": 0,
              "WebId": "d5ae2ee2-2a59-4b26-ba02-a577bb206da8"
            },
            {
              "$type": "Bespoke.Sph.Domain.Member, domain.sph",
              "FullName": null,
              "MemberCollection": {
                "$type": "Bespoke.Sph.Domain.ObjectCollection`1[[Bespoke.Sph.Domain.Member, domain.sph]], domain.sph",
                "$values": []
              },
              "FieldPermissionCollection": {
                "$type": "Bespoke.Sph.Domain.ObjectCollection`1[[Bespoke.Sph.Domain.FieldPermission, domain.sph]], domain.sph",
                "$values": []
              },
              "Name": "Postcode",
              "TypeName": "System.String, mscorlib",
              "IsNullable": false,
              "IsNotIndexed": false,
              "IsAnalyzed": false,
              "IsFilterable": false,
              "IsExcludeInAll": false,
              "Boost": 0,
              "WebId": "2322e7a8-d310-4ad2-b0f7-f16de872f825"
            },
            {
              "$type": "Bespoke.Sph.Domain.Member, domain.sph",
              "FullName": null,
              "MemberCollection": {
                "$type": "Bespoke.Sph.Domain.ObjectCollection`1[[Bespoke.Sph.Domain.Member, domain.sph]], domain.sph",
                "$values": []
              },
              "FieldPermissionCollection": {
                "$type": "Bespoke.Sph.Domain.ObjectCollection`1[[Bespoke.Sph.Domain.FieldPermission, domain.sph]], domain.sph",
                "$values": []
              },
              "Name": "City",
              "TypeName": "System.String, mscorlib",
              "IsNullable": false,
              "IsNotIndexed": false,
              "IsAnalyzed": false,
              "IsFilterable": false,
              "IsExcludeInAll": false,
              "Boost": 0,
              "WebId": "7b96048e-b9ba-4ea7-9a10-1044da7f4fbc"
            },
            {
              "$type": "Bespoke.Sph.Domain.Member, domain.sph",
              "FullName": null,
              "MemberCollection": {
                "$type": "Bespoke.Sph.Domain.ObjectCollection`1[[Bespoke.Sph.Domain.Member, domain.sph]], domain.sph",
                "$values": []
              },
              "FieldPermissionCollection": {
                "$type": "Bespoke.Sph.Domain.ObjectCollection`1[[Bespoke.Sph.Domain.FieldPermission, domain.sph]], domain.sph",
                "$values": []
              },
              "Name": "State",
              "TypeName": "System.String, mscorlib",
              "IsNullable": false,
              "IsNotIndexed": false,
              "IsAnalyzed": false,
              "IsFilterable": false,
              "IsExcludeInAll": false,
              "Boost": 0,
              "WebId": "937ea191-8392-488d-97d0-3601ebef18c4"
            },
            {
              "$type": "Bespoke.Sph.Domain.Member, domain.sph",
              "FullName": null,
              "MemberCollection": {
                "$type": "Bespoke.Sph.Domain.ObjectCollection`1[[Bespoke.Sph.Domain.Member, domain.sph]], domain.sph",
                "$values": []
              },
              "FieldPermissionCollection": {
                "$type": "Bespoke.Sph.Domain.ObjectCollection`1[[Bespoke.Sph.Domain.FieldPermission, domain.sph]], domain.sph",
                "$values": []
              },
              "Name": "Country",
              "TypeName": "System.String, mscorlib",
              "IsNullable": false,
              "IsNotIndexed": false,
              "IsAnalyzed": false,
              "IsFilterable": false,
              "IsExcludeInAll": false,
              "Boost": 0,
              "WebId": "36cd02ff-4cfb-42a2-8f4f-e79b716da6bc"
            }
          ]
        },
        "FieldPermissionCollection": {
          "$type": "Bespoke.Sph.Domain.ObjectCollection`1[[Bespoke.Sph.Domain.FieldPermission, domain.sph]], domain.sph",
          "$values": []
        },
        "Name": "HomeAddress",
        "TypeName": "System.Object, mscorlib",
        "IsNullable": false,
        "IsNotIndexed": false,
        "IsAnalyzed": false,
        "IsFilterable": false,
        "IsExcludeInAll": false,
        "Boost": 0,
        "WebId": "d6a20639-6a60-4cb7-a3c4-eec37c521bf5"
      },
      {
        "$type": "Bespoke.Sph.Domain.Member, domain.sph",
        "FullName": null,
        "MemberCollection": {
          "$type": "Bespoke.Sph.Domain.ObjectCollection`1[[Bespoke.Sph.Domain.Member, domain.sph]], domain.sph",
          "$values": []
        },
        "FieldPermissionCollection": {
          "$type": "Bespoke.Sph.Domain.ObjectCollection`1[[Bespoke.Sph.Domain.FieldPermission, domain.sph]], domain.sph",
          "$values": []
        },
        "Name": "Occupation",
        "TypeName": "System.String, mscorlib",
        "IsNullable": false,
        "IsNotIndexed": false,
        "IsAnalyzed": true,
        "IsFilterable": false,
        "IsExcludeInAll": false,
        "Boost": 0,
        "WebId": "66a6e80c-dd5e-4505-8731-09069afeeba5"
      },
      {
        "$type": "Bespoke.Sph.Domain.Member, domain.sph",
        "FullName": null,
        "MemberCollection": {
          "$type": "Bespoke.Sph.Domain.ObjectCollection`1[[Bespoke.Sph.Domain.Member, domain.sph]], domain.sph",
          "$values": []
        },
        "FieldPermissionCollection": {
          "$type": "Bespoke.Sph.Domain.ObjectCollection`1[[Bespoke.Sph.Domain.FieldPermission, domain.sph]], domain.sph",
          "$values": []
        },
        "Name": "Status",
        "TypeName": "System.String, mscorlib",
        "IsNullable": false,
        "IsNotIndexed": false,
        "IsAnalyzed": false,
        "IsFilterable": true,
        "IsExcludeInAll": false,
        "Boost": 0,
        "WebId": "1b1c8004-db3e-461c-bebd-e61eefcf64ac"
      },
      {
        "$type": "Bespoke.Sph.Domain.Member, domain.sph",
        "FullName": null,
        "MemberCollection": {
          "$type": "Bespoke.Sph.Domain.ObjectCollection`1[[Bespoke.Sph.Domain.Member, domain.sph]], domain.sph",
          "$values": []
        },
        "FieldPermissionCollection": {
          "$type": "Bespoke.Sph.Domain.ObjectCollection`1[[Bespoke.Sph.Domain.FieldPermission, domain.sph]], domain.sph",
          "$values": []
        },
        "Name": "Age",
        "TypeName": "System.Int32, mscorlib",
        "IsNullable": false,
        "IsNotIndexed": false,
        "IsAnalyzed": false,
        "IsFilterable": false,
        "IsExcludeInAll": false,
        "Boost": 0,
        "WebId": "0d42f390-a2e9-4c11-809d-ab46de6df9c1"
      },
      {
        "$type": "Bespoke.Sph.Domain.Member, domain.sph",
        "FullName": null,
        "MemberCollection": {
          "$type": "Bespoke.Sph.Domain.ObjectCollection`1[[Bespoke.Sph.Domain.Member, domain.sph]], domain.sph",
          "$values": []
        },
        "FieldPermissionCollection": {
          "$type": "Bespoke.Sph.Domain.ObjectCollection`1[[Bespoke.Sph.Domain.FieldPermission, domain.sph]], domain.sph",
          "$values": []
        },
        "Name": "Income",
        "TypeName": "System.Decimal, mscorlib",
        "IsNullable": false,
        "IsNotIndexed": false,
        "IsAnalyzed": false,
        "IsFilterable": false,
        "IsExcludeInAll": false,
        "Boost": 0,
        "WebId": "76c418fa-88c5-4d5f-9f5e-e05984c58818"
      },
      {
        "$type": "Bespoke.Sph.Domain.Member, domain.sph",
        "FullName": null,
        "MemberCollection": {
          "$type": "Bespoke.Sph.Domain.ObjectCollection`1[[Bespoke.Sph.Domain.Member, domain.sph]], domain.sph",
          "$values": []
        },
        "FieldPermissionCollection": {
          "$type": "Bespoke.Sph.Domain.ObjectCollection`1[[Bespoke.Sph.Domain.FieldPermission, domain.sph]], domain.sph",
          "$values": []
        },
        "Name": "Empty",
        "TypeName": "System.String, mscorlib",
        "IsNullable": true,
        "IsNotIndexed": false,
        "IsAnalyzed": false,
        "IsFilterable": false,
        "IsExcludeInAll": false,
        "Boost": 0,
        "WebId": "4d9f6fa6-a355-4900-ae58-1740c9f88cf3"
      },
      {
        "$type": "Bespoke.Sph.Domain.Member, domain.sph",
        "FullName": null,
        "MemberCollection": {
          "$type": "Bespoke.Sph.Domain.ObjectCollection`1[[Bespoke.Sph.Domain.Member, domain.sph]], domain.sph",
          "$values": []
        },
        "FieldPermissionCollection": {
          "$type": "Bespoke.Sph.Domain.ObjectCollection`1[[Bespoke.Sph.Domain.FieldPermission, domain.sph]], domain.sph",
          "$values": []
        },
        "Name": "Spouse",
        "TypeName": "System.String, mscorlib",
        "IsNullable": true,
        "IsNotIndexed": false,
        "IsAnalyzed": false,
        "IsFilterable": false,
        "IsExcludeInAll": false,
        "Boost": 0,
        "WebId": "892023c1-b8af-496f-a96d-50991e682d16"
      },
      {
        "$type": "Bespoke.Sph.Domain.Member, domain.sph",
        "FullName": null,
        "MemberCollection": {
          "$type": "Bespoke.Sph.Domain.ObjectCollection`1[[Bespoke.Sph.Domain.Member, domain.sph]], domain.sph",
          "$values": []
        },
        "FieldPermissionCollection": {
          "$type": "Bespoke.Sph.Domain.ObjectCollection`1[[Bespoke.Sph.Domain.FieldPermission, domain.sph]], domain.sph",
          "$values": []
        },
        "Name": "MaritalStatus",
        "TypeName": "System.String, mscorlib",
        "IsNullable": true,
        "IsNotIndexed": false,
        "IsAnalyzed": false,
        "IsFilterable": true,
        "IsExcludeInAll": false,
        "Boost": 0,
        "WebId": "8adc580b-efb3-46d8-b40b-f4828b81398d"
      }
    ]
  },
  "BusinessRuleCollection": {
    "$type": "Bespoke.Sph.Domain.ObjectCollection`1[[Bespoke.Sph.Domain.BusinessRule, domain.sph]], domain.sph",
    "$values": [
      {
        "$type": "Bespoke.Sph.Domain.BusinessRule, domain.sph",
        "RuleCollection": {
          "$type": "Bespoke.Sph.Domain.ObjectCollection`1[[Bespoke.Sph.Domain.Rule, domain.sph]], domain.sph",
          "$values": [
            {
              "$type": "Bespoke.Sph.Domain.Rule, domain.sph",
              "Left": {
                "$type": "Bespoke.Sph.Domain.DocumentField, domain.sph",
                "XPath": "",
                "NamespacePrefix": "",
                "TypeName": "",
                "Path": "Dob",
                "Name": "Dob",
                "Note": "",
                "WebId": "a0001501-8c3a-4457-944c-e64db0afd66d"
              },
              "Right": {
                "$type": "Bespoke.Sph.Domain.FunctionField, domain.sph",
                "Script": "DateTime.Now",
                "Name": "Now",
                "Note": "",
                "WebId": "d374684c-e893-4507-aff1-3e1ce9ee9ddf"
              },
              "Operator": "Lt",
              "WebId": "82cdf197-f8d2-45b1-be66-0577d19c3c21"
            }
          ]
        },
        "FilterCollection": {
          "$type": "Bespoke.Sph.Domain.ObjectCollection`1[[Bespoke.Sph.Domain.Rule, domain.sph]], domain.sph",
          "$values": []
        },
        "Description": "",
        "Name": "Dob",
        "ErrorLocation": "",
        "ErrorMessage": "Dob cannot be future date",
        "WebId": "e12558cb-c8a5-43e0-9f1f-2de05c42879e"
      },
      {
        "$type": "Bespoke.Sph.Domain.BusinessRule, domain.sph",
        "RuleCollection": {
          "$type": "Bespoke.Sph.Domain.ObjectCollection`1[[Bespoke.Sph.Domain.Rule, domain.sph]], domain.sph",
          "$values": [
            {
              "$type": "Bespoke.Sph.Domain.Rule, domain.sph",
              "Left": {
                "$type": "Bespoke.Sph.Domain.DocumentField, domain.sph",
                "XPath": "",
                "NamespacePrefix": "",
                "TypeName": "",
                "Path": "MaritalStatus",
                "Name": "MaritalStatus",
                "Note": "",
                "WebId": "bb019a80-a80d-4266-9592-c15ea8fd813b"
              },
              "Right": {
                "$type": "Bespoke.Sph.Domain.ConstantField, domain.sph",
                "TypeName": "System.String, mscorlib",
                "Value": "Single",
                "Name": "Single",
                "Note": "",
                "WebId": "3f251526-3e9b-4a18-9a94-99fb2cb20521"
              },
              "Operator": "Eq",
              "WebId": "8c1a203c-a748-420c-bb89-bfb9f2f60bf5"
            }
          ]
        },
        "FilterCollection": {
          "$type": "Bespoke.Sph.Domain.ObjectCollection`1[[Bespoke.Sph.Domain.Rule, domain.sph]], domain.sph",
          "$values": [
            {
              "$type": "Bespoke.Sph.Domain.Rule, domain.sph",
              "Left": {
                "$type": "Bespoke.Sph.Domain.DocumentField, domain.sph",
                "XPath": "",
                "NamespacePrefix": "",
                "TypeName": "",
                "Path": "Age",
                "Name": "Age",
                "Note": "",
                "WebId": "383d3b32-1708-4b41-8940-dbc3c1287116"
              },
              "Right": {
                "$type": "Bespoke.Sph.Domain.ConstantField, domain.sph",
                "TypeName": "System.Int32, mscorlib",
                "Value": 10,
                "Name": "10",
                "Note": "",
                "WebId": "22796ba8-b3ab-4db7-bf84-9f3239212206"
              },
              "Operator": "Le",
              "WebId": "52a9afdf-fcc7-4c6f-b206-ab9f4583a0d6"
            }
          ]
        },
        "Description": "Too young to get married",
        "Name": "ChildMarriage",
        "ErrorLocation": "",
        "ErrorMessage": "Too young to get married",
        "WebId": "d7cb6bd5-5a17-4ec8-a6a6-20865d67246b"
      }
    ]
  },
  "EntityOperationCollection": {
    "$type": "Bespoke.Sph.Domain.ObjectCollection`1[[Bespoke.Sph.Domain.EntityOperation, domain.sph]], domain.sph",
    "$values": [
      {
        "$type": "Bespoke.Sph.Domain.EntityOperation, domain.sph",
        "EntityPermissionCollection": {
          "$type": "Bespoke.Sph.Domain.ObjectCollection`1[[Bespoke.Sph.Domain.EntityPermission, domain.sph]], domain.sph",
          "$values": []
        },
        "Rules": {
          "$type": "Bespoke.Sph.Domain.ObjectCollection`1[[System.String, mscorlib]], domain.sph",
          "$values": [
            "Dob"
          ]
        },
        "Permissions": {
          "$type": "Bespoke.Sph.Domain.ObjectCollection`1[[System.String, mscorlib]], domain.sph",
          "$values": [
            "Anonymous"
          ]
        },
        "SetterActionChildCollection": {
          "$type": "Bespoke.Sph.Domain.ObjectCollection`1[[Bespoke.Sph.Domain.SetterActionChild, domain.sph]], domain.sph",
          "$values": [
            {
              "$type": "Bespoke.Sph.Domain.SetterActionChild, domain.sph",
              "Path": "Mrn",
              "Field": {
                "$type": "Bespoke.Sph.Domain.FunctionField, domain.sph",
                "Script": "string.Format(\"{0:yyyyMMdd}-{1:Mdss}\",item.Dob,DateTime.Now)",
                "Name": "Mrn with DOB",
                "Note": "",
                "WebId": "35dff2c2-7693-4832-8c5f-dc5ef177a40b"
              },
              "WebId": "ec52a232-a300-4671-97c3-debd580576da"
            },
            {
              "$type": "Bespoke.Sph.Domain.SetterActionChild, domain.sph",
              "Path": "Status",
              "Field": {
                "$type": "Bespoke.Sph.Domain.ConstantField, domain.sph",
                "TypeName": "System.String, mscorlib",
                "Value": "New",
                "Name": "New",
                "Note": "",
                "WebId": "7368d50e-2982-4dcb-b77e-1bf636aec53c"
              },
              "WebId": "b414e6e9-9acb-4ba1-86ff-13f78db875f6"
            }
          ]
        },
        "Name": "Register",
        "SuccessMessage": "Ok done",
        "ShowSuccessMessage": false,
        "NavigateSuccessUrl": "#patient",
        "SuccessCommand": "",
        "WebId": "2dfe6dc4-2757-4b67-ae7d-7d57e6a2dc0d"
      },
      {
        "$type": "Bespoke.Sph.Domain.EntityOperation, domain.sph",
        "EntityPermissionCollection": {
          "$type": "Bespoke.Sph.Domain.ObjectCollection`1[[Bespoke.Sph.Domain.EntityPermission, domain.sph]], domain.sph",
          "$values": []
        },
        "Rules": {
          "$type": "Bespoke.Sph.Domain.ObjectCollection`1[[System.String, mscorlib]], domain.sph",
          "$values": []
        },
        "Permissions": {
          "$type": "Bespoke.Sph.Domain.ObjectCollection`1[[System.String, mscorlib]], domain.sph",
          "$values": [
            "Everybody"
          ]
        },
        "SetterActionChildCollection": {
          "$type": "Bespoke.Sph.Domain.ObjectCollection`1[[Bespoke.Sph.Domain.SetterActionChild, domain.sph]], domain.sph",
          "$values": [
            {
              "$type": "Bespoke.Sph.Domain.SetterActionChild, domain.sph",
              "Path": "Status",
              "Field": {
                "$type": "Bespoke.Sph.Domain.ConstantField, domain.sph",
                "TypeName": "System.String, mscorlib",
                "Value": "Dischaged",
                "Name": "Dischaged",
                "Note": "",
                "WebId": "75696db4-ad26-48c5-84e9-ec88b4e82f6d"
              },
              "WebId": "0e22d6e6-f3af-46ff-ad65-d27a15c48f06"
            }
          ]
        },
        "Name": "Discharge",
        "SuccessMessage": "Done",
        "ShowSuccessMessage": false,
        "NavigateSuccessUrl": "#patient",
        "SuccessCommand": "",
        "WebId": "3fd43fb0-ee29-4933-875c-9c2330e81bbe"
      },
      {
        "$type": "Bespoke.Sph.Domain.EntityOperation, domain.sph",
        "EntityPermissionCollection": {
          "$type": "Bespoke.Sph.Domain.ObjectCollection`1[[Bespoke.Sph.Domain.EntityPermission, domain.sph]], domain.sph",
          "$values": []
        },
        "Rules": {
          "$type": "Bespoke.Sph.Domain.ObjectCollection`1[[System.String, mscorlib]], domain.sph",
          "$values": []
        },
        "Permissions": {
          "$type": "Bespoke.Sph.Domain.ObjectCollection`1[[System.String, mscorlib]], domain.sph",
          "$values": [
            "Everybody"
          ]
        },
        "SetterActionChildCollection": {
          "$type": "Bespoke.Sph.Domain.ObjectCollection`1[[Bespoke.Sph.Domain.SetterActionChild, domain.sph]], domain.sph",
          "$values": [
            {
              "$type": "Bespoke.Sph.Domain.SetterActionChild, domain.sph",
              "Path": "Status",
              "Field": {
                "$type": "Bespoke.Sph.Domain.ConstantField, domain.sph",
                "TypeName": "System.String, mscorlib",
                "Value": "Transferred",
                "Name": "Transferred",
                "Note": "",
                "WebId": "3ca256b9-6cec-4fc8-8345-7c78678aca63"
              },
              "WebId": "3a91284f-ca47-4976-9a93-dab80642536c"
            }
          ]
        },
        "Name": "Transfer",
        "SuccessMessage": "Done",
        "ShowSuccessMessage": false,
        "NavigateSuccessUrl": "#patient",
        "SuccessCommand": "",
        "WebId": "f017a0c7-b152-4cb4-8914-188b182a046a"
      },
      {
        "$type": "Bespoke.Sph.Domain.EntityOperation, domain.sph",
        "EntityPermissionCollection": {
          "$type": "Bespoke.Sph.Domain.ObjectCollection`1[[Bespoke.Sph.Domain.EntityPermission, domain.sph]], domain.sph",
          "$values": []
        },
        "Rules": {
          "$type": "Bespoke.Sph.Domain.ObjectCollection`1[[System.String, mscorlib]], domain.sph",
          "$values": []
        },
        "Permissions": {
          "$type": "Bespoke.Sph.Domain.ObjectCollection`1[[System.String, mscorlib]], domain.sph",
          "$values": [
            "Everybody"
          ]
        },
        "SetterActionChildCollection": {
          "$type": "Bespoke.Sph.Domain.ObjectCollection`1[[Bespoke.Sph.Domain.SetterActionChild, domain.sph]], domain.sph",
          "$values": [
            {
              "$type": "Bespoke.Sph.Domain.SetterActionChild, domain.sph",
              "Path": "Status",
              "Field": {
                "$type": "Bespoke.Sph.Domain.ConstantField, domain.sph",
                "TypeName": "System.String, mscorlib",
                "Value": "Admitted",
                "Name": "Admitted",
                "Note": "",
                "WebId": "2a202489-fb17-4cb7-91d6-d1b24ba966e0"
              },
              "WebId": "1b76de49-5a32-45d2-b037-9ef091c8b5b2"
            }
          ]
        },
        "Name": "Admit",
        "SuccessMessage": "OK done",
        "ShowSuccessMessage": false,
        "NavigateSuccessUrl": "#patient",
        "SuccessCommand": "",
        "WebId": "c9da7b5e-2a70-46a9-9b04-cd962a3bf368"
      }
    ]
  },
  "AuthorizedRoleCollection": {
    "$type": "Bespoke.Sph.Domain.ObjectCollection`1[[System.String, mscorlib]], domain.sph",
    "$values": []
  },
  "EntityDefinitionId": 2002,
  "Name": "Patient",
  "Plural": "Patients",
  "IconStoreId": "1527fe01-e066-4208-bb15-6ddb84330c2b",
  "IconClass": "fa fa-user",
  "RecordName": "Mrn",
  "IsPublished": true,
  "IsShowOnNavigationBar": true,
  "CreatedBy": null,
  "CreatedDate": "0001-01-01T00:00:00",
  "ChangedBy": "admin",
  "ChangedDate": "2014-04-15T09:53:38.8786907+08:00",
  "WebId": "bd9f6160-8d69-4b1a-94eb-b123a1523267"
}